{
    "key": "group_617950aaf09d4",
    "title": "Footer Mobile Link",
    "fields": [
        {
            "key": "field_617950b9369d2",
            "label": "Fotter button",
            "name": "show_button_footer",
            "type": "true_false",
            "instructions": "",
            "required": 0,
            "conditional_logic": 0,
            "wrapper": {
                "width": "33.333",
                "class": "",
                "id": ""
            },
            "message": "",
            "default_value": 0,
            "ui": 0,
            "ui_on_text": "",
            "ui_off_text": ""
        },
        {
            "key": "field_6182abed334a6",
            "label": "button android",
            "name": "button_footer_android",
            "type": "link",
            "instructions": "",
            "required": 0,
            "conditional_logic": 0,
            "wrapper": {
                "width": "33.333",
                "class": "",
                "id": ""
            },
            "return_format": "array"
        },
        {
            "key": "field_6182ac0d334a7",
            "label": "button ios",
            "name": "button_footer_ios",
            "type": "link",
            "instructions": "",
            "required": 0,
            "conditional_logic": 0,
            "wrapper": {
                "width": "33.333",
                "class": "",
                "id": ""
            },
            "return_format": "array"
        }
    ],
    "location": [
        [
            {
                "param": "post_template",
                "operator": "==",
                "value": "mobile-app.php"
            }
        ]
    ],
    "menu_order": 0,
    "position": "side",
    "style": "default",
    "label_placement": "top",
    "instruction_placement": "label",
    "hide_on_screen": "",
    "active": true,
    "description": "",
    "modified": 1635953827
}