{
    "key": "group_60648c98034e2",
    "title": "Block with Posts",
    "fields": [
        {
            "key": "field_606c3bbffdb69",
            "label": "Posts",
            "name": "",
            "type": "tab",
            "instructions": "",
            "required": 0,
            "conditional_logic": 0,
            "wrapper": {
                "width": "",
                "class": "",
                "id": ""
            },
            "placement": "left",
            "endpoint": 0
        },
        {
            "key": "field_60648caac3034",
            "label": "Static posts",
            "name": "list_posts",
            "type": "relationship",
            "instructions": "",
            "required": 0,
            "conditional_logic": [
                [
                    {
                        "field": "field_606c1a854e84f",
                        "operator": "==empty"
                    }
                ]
            ],
            "wrapper": {
                "width": "",
                "class": "",
                "id": ""
            },
            "post_type": [
                "post",
                "page"
            ],
            "taxonomy": "",
            "filters": [
                "search",
                "post_type",
                "taxonomy"
            ],
            "elements": [
                "featured_image"
            ],
            "min": 1,
            "max": 4,
            "return_format": "id"
        },
        {
            "key": "field_606c1a854e84f",
            "label": "Taxonomy posts",
            "name": "taxonomy",
            "type": "taxonomy",
            "instructions": "",
            "required": 0,
            "conditional_logic": [
                [
                    {
                        "field": "field_60648caac3034",
                        "operator": "==empty"
                    }
                ]
            ],
            "wrapper": {
                "width": "",
                "class": "",
                "id": ""
            },
            "taxonomy": "category",
            "field_type": "checkbox",
            "add_term": 0,
            "save_terms": 0,
            "load_terms": 0,
            "return_format": "id",
            "multiple": 0,
            "allow_null": 0
        },
        {
            "key": "field_606d857e3f8b1",
            "label": "Count posts",
            "name": "count_posts",
            "type": "range",
            "instructions": "",
            "required": 0,
            "conditional_logic": 0,
            "wrapper": {
                "width": "",
                "class": "",
                "id": ""
            },
            "default_value": 4,
            "min": 1,
            "max": 4,
            "step": 1,
            "prepend": "",
            "append": ""
        },
        {
            "key": "field_6065aa3be42e1",
            "label": "Title for block",
            "name": "",
            "type": "tab",
            "instructions": "",
            "required": 0,
            "conditional_logic": 0,
            "wrapper": {
                "width": "",
                "class": "",
                "id": ""
            },
            "placement": "left",
            "endpoint": 0
        },
        {
            "key": "field_6065ac49e42e3",
            "label": "Show title?",
            "name": "show_title",
            "type": "true_false",
            "instructions": "",
            "required": 0,
            "conditional_logic": 0,
            "wrapper": {
                "width": "",
                "class": "",
                "id": ""
            },
            "message": "",
            "default_value": 0,
            "ui": 1,
            "ui_on_text": "",
            "ui_off_text": ""
        },
        {
            "key": "field_6065ac63e42e4",
            "label": "Title",
            "name": "title_block",
            "type": "text",
            "instructions": "",
            "required": 0,
            "conditional_logic": [
                [
                    {
                        "field": "field_6065ac49e42e3",
                        "operator": "==",
                        "value": "1"
                    }
                ]
            ],
            "wrapper": {
                "width": "",
                "class": "",
                "id": ""
            },
            "default_value": "",
            "placeholder": "",
            "prepend": "",
            "append": "",
            "maxlength": ""
        },
        {
            "key": "field_6065acb769c32",
            "label": "Button \"More..\"",
            "name": "",
            "type": "tab",
            "instructions": "",
            "required": 0,
            "conditional_logic": 0,
            "wrapper": {
                "width": "",
                "class": "",
                "id": ""
            },
            "placement": "left",
            "endpoint": 0
        },
        {
            "key": "field_6065ad1069c33",
            "label": "Show button?",
            "name": "show_button",
            "type": "true_false",
            "instructions": "",
            "required": 0,
            "conditional_logic": 0,
            "wrapper": {
                "width": "",
                "class": "",
                "id": ""
            },
            "message": "",
            "default_value": 0,
            "ui": 1,
            "ui_on_text": "",
            "ui_off_text": ""
        },
        {
            "key": "field_6065ad2a69c34",
            "label": "Text for button",
            "name": "text_for_button",
            "type": "text",
            "instructions": "",
            "required": 0,
            "conditional_logic": [
                [
                    {
                        "field": "field_6065ad1069c33",
                        "operator": "==",
                        "value": "1"
                    }
                ]
            ],
            "wrapper": {
                "width": "",
                "class": "",
                "id": ""
            },
            "default_value": "",
            "placeholder": "",
            "prepend": "",
            "append": "",
            "maxlength": ""
        },
        {
            "key": "field_6065ad6969c35",
            "label": "Link",
            "name": "link_button",
            "type": "url",
            "instructions": "",
            "required": 0,
            "conditional_logic": [
                [
                    {
                        "field": "field_6065ad1069c33",
                        "operator": "==",
                        "value": "1"
                    }
                ]
            ],
            "wrapper": {
                "width": "",
                "class": "",
                "id": ""
            },
            "default_value": "",
            "placeholder": ""
        },
        {
            "key": "field_6065ad918ab91",
            "label": "Link \"Read more...\"",
            "name": "",
            "type": "tab",
            "instructions": "",
            "required": 0,
            "conditional_logic": 0,
            "wrapper": {
                "width": "",
                "class": "",
                "id": ""
            },
            "placement": "top",
            "endpoint": 0
        },
        {
            "key": "field_6065ada98ab92",
            "label": "Text for link",
            "name": "text_for_link",
            "type": "text",
            "instructions": "",
            "required": 0,
            "conditional_logic": 0,
            "wrapper": {
                "width": "",
                "class": "",
                "id": ""
            },
            "default_value": "",
            "placeholder": "",
            "prepend": "",
            "append": "",
            "maxlength": ""
        },
        {
            "key": "field_60672917e0357",
            "label": "Tag wrapper",
            "name": "",
            "type": "tab",
            "instructions": "",
            "required": 0,
            "conditional_logic": 0,
            "wrapper": {
                "width": "",
                "class": "",
                "id": ""
            },
            "placement": "top",
            "endpoint": 0
        },
        {
            "key": "field_6067289ce0356",
            "label": "Tag",
            "name": "tag_wrapper",
            "type": "select",
            "instructions": "",
            "required": 0,
            "conditional_logic": 0,
            "wrapper": {
                "width": "",
                "class": "",
                "id": ""
            },
            "choices": {
                "section": "section",
                "div": "div"
            },
            "default_value": "section",
            "allow_null": 0,
            "multiple": 0,
            "ui": 0,
            "return_format": "value",
            "ajax": 0,
            "placeholder": ""
        }
    ],
    "location": [
        [
            {
                "param": "block",
                "operator": "==",
                "value": "acf\/block-post"
            }
        ]
    ],
    "menu_order": 0,
    "position": "normal",
    "style": "default",
    "label_placement": "top",
    "instruction_placement": "label",
    "hide_on_screen": "",
    "active": true,
    "description": "",
    "modified": 1618314266
}